ndx_ecog/__init__.py
ndx_ecog/ecog.py
ndx_ecog/spec/ndx-ecog.extensions.yaml
ndx_ecog/spec/ndx-ecog.namespace.yaml
tests/__init__.py
tests/test_ndx_ecog.py
ndx_ecog-0.1.1.dist-info/LICENSE.txt
ndx_ecog-0.1.1.dist-info/METADATA
ndx_ecog-0.1.1.dist-info/WHEEL
ndx_ecog-0.1.1.dist-info/top_level.txt
ndx_ecog-0.1.1.dist-info/RECORD
