Metadata-Version: 2.1
Name: ndx-ecog
Version: 0.1.1
Summary: An NWB extension for storing the cortical surface of subjects in ECoG experiments
Home-page: UNKNOWN
Author: Ben Dichter
Author-email: ben.dichter@gmail.com
License: BSD 3-Clause
Platform: UNKNOWN
Classifier: Intended Audience :: Developers
Classifier: Intended Audience :: Science/Research
Requires-Dist: pynwb (>=1.1.2)
